katlas/__init__.py
katlas/_modidx.py
katlas/clustering.py
katlas/common.py
katlas/core.py
katlas/data.py
katlas/dnn.py
katlas/feature.py
katlas/pathway.py
katlas/plot.py
katlas/pssm.py
katlas/score.py
katlas/statistics.py
katlas/train.py
katlas/utils.py
python_katlas-2025.11.9.dist-info/licenses/LICENSE
python_katlas-2025.11.9.dist-info/METADATA
python_katlas-2025.11.9.dist-info/WHEEL
python_katlas-2025.11.9.dist-info/entry_points.txt
python_katlas-2025.11.9.dist-info/top_level.txt
python_katlas-2025.11.9.dist-info/RECORD
