Metadata-Version: 2.4
Name: python-katlas
Version: 2025.11.9
Summary: tools for predicting kinome specificities
Home-page: https://github.com/sky1ove/katlas
Author: lily
Author-email: lcai888666@gmail.com
License: Apache Software License 2.0
Keywords: nbdev jupyter notebook python
Classifier: Development Status :: 4 - Beta
Classifier: Intended Audience :: Developers
Classifier: Natural Language :: English
Classifier: Programming Language :: Python :: 3.7
Classifier: Programming Language :: Python :: 3.8
Classifier: Programming Language :: Python :: 3.9
Classifier: Programming Language :: Python :: 3.10
Classifier: License :: OSI Approved :: Apache Software License
Requires-Python: >=3.7
License-File: LICENSE
Requires-Dist: pandas
Requires-Dist: gdown
Requires-Dist: statsmodels
Requires-Dist: statannotations
Requires-Dist: fastparquet
Requires-Dist: pyarrow
Requires-Dist: tqdm
Requires-Dist: logomaker-kinase
Requires-Dist: seaborn
Requires-Dist: bokeh
Requires-Dist: reactome2py
Requires-Dist: adjustText
Requires-Dist: scikit-learn
Requires-Dist: umap-learn
Requires-Dist: ipywidgets
Requires-Dist: biopython
Provides-Extra: dev
Requires-Dist: nbdev; extra == "dev"
Requires-Dist: pyngrok; extra == "dev"
Requires-Dist: fastai; extra == "dev"
Requires-Dist: fairscale; extra == "dev"
Requires-Dist: fair-esm; extra == "dev"
Requires-Dist: rdkit; extra == "dev"
Requires-Dist: openpyxl; extra == "dev"
Requires-Dist: transformers; extra == "dev"
Requires-Dist: sentencepiece; extra == "dev"
Dynamic: author
Dynamic: author-email
Dynamic: classifier
Dynamic: description
Dynamic: description-content-type
Dynamic: home-page
Dynamic: keywords
Dynamic: license
Dynamic: license-file
Dynamic: provides-extra
Dynamic: requires-dist
Dynamic: requires-python
Dynamic: summary
